SEQUENTIAL/decode_writeback.v
//decode and write_back
//i wrote both the modules at the same time bacause assigning a register directly with a value and passing it to decode is not happeing in decode so if we give registers
//as output and assign values to them in decode it self we will get the correct answer

module decode(clk, icode, rA, rB,
              reg_f0,reg_f1,reg_f2,reg_f3,reg_f4,reg_f5,reg_f6,reg_f7,reg_f8,reg_f9,reg_f10,reg_f11,reg_f12,reg_f13,reg_f14,
              valA,valB,cnd,valM,valE);

    input clk,cnd;
    input [3:0] icode,rA,rB;
    output reg signed[63:0] reg_f0,reg_f1,reg_f2,reg_f3,reg_f4,reg_f5,reg_f6,reg_f7,reg_f8,reg_f9,reg_f10,reg_f11,reg_f12,reg_f13,reg_f14; //we have 15 registers in y86-64 processor
    output reg signed[63:0] valA,valB; //value is updated by a 64 bit number from memory and reg data type is used because we will update the values of outputs conditionally
    reg signed[63:0] temp_memory[0:14];
    input signed[63:0] valE;
    input[63:0] valM;

    initial begin
        //we can directly access the registers using RA values so we assign them to a temp_memory where we can access values using indexes
        temp_memory[0] = 64'd12;        //rax
        temp_memory[1] = 64'd10;        //rcx
        temp_memory[2] = 64'd101;       //rdx
        temp_memory[3] = 64'd3;       //rbx
        temp_memory[4] = 64'd254;       //rsp
        temp_memory[5] = 64'd50;        //rbp
        temp_memory[6] = -64'd143;      //rsi
        temp_memory[7] = 64'd10000;     //rdi
        temp_memory[8] = 64'd990000;    //r8
        temp_memory[9] = -64'd12345;    //r9
        temp_memory[10] = 64'd12345;    //r10
        temp_memory[11] = 64'd10112;    //r11
        temp_memory[12] = 64'd0;        //r12
        temp_memory[13] = 64'd1567;     //r13
        temp_memory[14] = 64'd8643;     //r14
    end
    always @(*) //executes when any of the inputs is changed
    //in decode instruction we read the operands valA and valB from the register file
    begin 
        if(icode == 4'h2 | icode == 4'h3)begin
            valB = 64'd0; //irmovq and cmovxx condition is joined together
        end
        if(icode == 4'h2 | icode == 4'h4 | icode == 4'h6 | icode == 4'hA)begin //cmovxx,rmmovq,opq,pushq
            valA = temp_memory[rA];
        end
        if(icode == 4'h4 | icode == 4'h5 | icode == 4'h6)begin 
            valB = temp_memory[rB]; //rmmovq , mrmovq , opq
        end
        if(icode == 4'h8 | icode == 4'h9 | icode == 4'hA | icode == 4'hB)begin
            valB = temp_memory[4]; //call,return,pushq,popq
        end
        if(icode == 4'h9 | icode == 4'hB)begin//return popq

            valA = temp_memory[4]; //for push and popq the values are taken from %rsp register whose value is 4
        end      
    end

////////////////              //////////////////
///////////////  write back  //////////////////
//////////////              //////////////////

    always@(posedge clk)begin 

        if(icode==4'h3 | icode==4'h6)begin
            temp_memory[rB]=valE; //irmovq and opq
        end
        if(icode==4'h5 | icode==4'hB)begin 
            temp_memory[rA] = valM; //mrmovq and popq
        end
        if(icode==4'h8 | icode==4'h9 | icode==4'hA | icode==4'hB) begin
            temp_memory[4] = valE; //call,ret,pushq,popq
        end
        if(icode==4'h2)begin
            if(cnd)begin//cmovxx
                temp_memory[rB]=valE;
            end
        end
        reg_f0 <= temp_memory[0];
        reg_f1 <= temp_memory[1];
        reg_f2 <= temp_memory[2];
        reg_f3 <= temp_memory[3];
        reg_f4 <= temp_memory[4];
        reg_f5 <= temp_memory[5];
        reg_f6 <= temp_memory[6];
        reg_f7 <= temp_memory[7];
        reg_f8 <= temp_memory[8];
        reg_f9 <= temp_memory[9];
        reg_f10 <= temp_memory[10];
        reg_f11 <= temp_memory[11];
        reg_f12 <= temp_memory[12];
        reg_f13 <= temp_memory[13];
        reg_f14 <= temp_memory[14];
    end
endmodule

SEQUENTIAL/fetch.v
module fetch(clk,icode,ifun,rA,rB,valc,valP,PC,invalid_instr,mem_error,halt,instr);
    input clk;    
    input [63:0] PC; //this points to the address of instruction;
    input [0:79]instr; // the maximum length of any instruction is 10bytes = 80bits
    output reg [3:0] icode,ifun;
    output reg [63:0] valc; //this is where the displacement or destination value in jump is stores;
    output reg [3:0] rA,rB; //registers which stores  the parameters
    output reg [63:0] valP; //updated PC value
    output reg invalid_instr = 0, mem_error = 0; //flages to check memory and second flag is to check valid instruction
    output reg halt=0;
    always @(*) // here * represents all the inputs and any changes in input is sensed
    begin
        if(PC>255)//here 256 may vary based on our input registers used
        begin
            mem_error = 1;
        end
        {icode,ifun} = instr[0:7];//first register contains icode and ifun
        //now we can know the length of instruction by icode and ifun
        if(icode == 4'h0) //halt
        begin 
            halt =1;
            valP = PC+1;
        end
        else if(icode == 4'h1) //nop
        begin
            valP = PC + 1;
        end
        else if(icode == 4'h2) // cmovq
        begin
            {rA,rB} = instr[8:15]; //1byte for rA and rB
            valP = PC+2;
        end
        else if(icode == 4'h3)//irmovq
        begin
            {rA,rB,valc} = instr[8:79]; //1byte for rA and rB and 8bytes for valc
            valP = PC+10; //10byte instruction
        end
        else if(icode == 4'h4) //rmmovq
        begin 
            {rA,rB,valc}=instr[8:79];
            valP = PC+10; //10byte instruction
        end
        else if(icode == 4'h5) //mrmovq
        begin
            {rA,rB,valc} = instr[8:79];
            valP = PC+10;//10byte instruction
        end
        else if(icode == 4'h6) //OPq
        begin 
            {rA,rB}=instr[8:15];
            valP=PC+2;
        end
        else if(icode == 4'h7) //jxx
        begin 
            valc = instr[8:71]; // no ra and rb in jump instruction
            valP = PC+9;
        end
        else if(icode == 4'h8) //call
        begin 

            valc = instr[8:71]; // stores the current PC address so that it can be called after the function is executed
            valP = PC+9;
        end
        else if(icode == 4'h9) //return
        begin
            valP = PC +1;
        end
        else if(icode == 4'hA) //pushq
        begin 
            {rA,rB}=instr[8:15];
            valP=PC+2;
        end
        else if(icode == 4'hB) //popq
        begin
            {rA,rB}=instr[8:15];
            valP=PC+2;
        end
        else
        begin 
            invalid_instr = 1'b1;
        end
    end
endmodule

SEQUENTIAL/decode_tb.v
`include "fetch.v"
`include "decode_writeback.v"
module decode_tb;
    //inputs
    reg clk;
    reg [63:0]PC;
    //outputs
    wire [3:0] icode,ifun,rA,rB;
    wire signed[63:0] valc;
    wire  [63:0]valP;
    wire mem_error,invalid_instr;
    reg [7:0] instr_memory[0:255];//memory that contains all the instructions
    reg [0:79] instr; //instruction with 10bytes
    wire signed [63:0]valA,valB,valE;
    wire signed [63:0]valM;
    wire halt;
    wire cnd = 1;
    wire signed[63:0] reg_f0,reg_f1,reg_f2,reg_f3,reg_f4,reg_f5,reg_f6,reg_f7,reg_f8,reg_f9,reg_f10,reg_f11,reg_f12,reg_f13,reg_f14;

    

/////////////////////////////////////////////////////////////////////////////////////////
fetch fetch_call(clk,icode,ifun,rA,rB,valc,valP,PC,invalid_instr,mem_error,halt,instr);
/////////////////////////////////////////////////////////////////////////////////////////


////////////////////////////////////////////////////////////////////////////////////////////////////////////////////////////////////
decode decode_call(clk, icode, rA, rB,
              reg_f0,reg_f1,reg_f2,reg_f3,reg_f4,reg_f5,reg_f6,reg_f7,reg_f8,reg_f9,reg_f10,reg_f11,reg_f12,reg_f13,reg_f14,
              valA,valB,cnd,valM,valE);
///////////////////////////////////////////////////////////////////////////////////////////////////////////////////////////////////
always @(PC) begin
    instr = {instr_memory[PC],instr_memory[PC+1],instr_memory[PC+2],
            instr_memory[PC+3],instr_memory[PC+4],instr_memory[PC+5],
            instr_memory[PC+6],instr_memory[PC+7],instr_memory[PC+8],
            instr_memory[PC+9]};  
end

always@(icode) begin 
    if(halt == 1)begin
        $finish; //stops the program if halt is encountered
    end
end
always@(mem_error) begin 
    if(mem_error == 1)begin
        $display("memory full...so halting the program\n");
        $finish;
    end
end
always@(invalid_instr) begin 
    if(invalid_instr == 1)begin
        $display("warning you have given an invald instruction so we will move to the next instruction now automatically pc is updated\nnow PC = %d",PC+1,"\n");
        PC = PC +1;
    end
end
always #10 begin clk = ~clk; end //updating clk for 10ns
always @(posedge clk) begin PC<=valP; end // updating PC so that new pc value is updated

initial begin
    $dumpfile("decode_tb.vcd");
    $dumpvars(0, decode_tb);
    clk = 0;
    PC = 64'd19;

end

always @(posedge clk)begin $display("clk=%d icode=%h ifun=%h rA=%d rB=%d,valc=%d,valP=%d,valA = %d and valB = %d\n",clk,icode,ifun,rA,rB,valc,valP,valA,valB); end

initial begin

   instr_memory[19]  = 8'h10; //nop pc = 1

    instr_memory[20] = 8'h20; //rrmovq
    instr_memory[21]  = 8'h01; //ra = 0 and rb =1 and pc = pc + 2 = 3

    // instr_memory[3]  = 8'h30; //irmovq
    // instr_memory[4]  = 8'h02; //F and rb = 2
    // instr_memory[5]  = 8'hFF; //8bytes
    // instr_memory[6]  = 8'hFF;
    // instr_memory[7]  = 8'hFF;
    // instr_memory[8]  = 8'hFF;
    // instr_memory[9]  = 8'hFF;
    // instr_memory[10]  = 8'hFF;
    // instr_memory[11]  = 8'hFF;
    // instr_memory[12]  = 8'hFF; //pc = pc +10 = 13

    instr_memory[22]  = 8'h60; //opq add
    instr_memory[23]  = 8'h23; //ra and rb pc = pc +2  = 15   
    // instr_memory[15]  = 8'h70; //jmp
    // instr_memory[16]  = 8'h00; //8bytes address
    // instr_memory[17]  = 8'h00;
    // instr_memory[18]  = 8'h00;
    // instr_memory[19]  = 8'h00;
    // instr_memory[20]  = 8'h00;
    // instr_memory[21]  = 8'h00;
    // instr_memory[22]  = 8'h11;
    // instr_memory[23]  = 8'h10; //pc = pc+9 = 24

    instr_memory[24]  = 8'h80; //call
    instr_memory[25]  = 8'h00;//8byte destination
    instr_memory[26]  = 8'h00;
    instr_memory[27]  = 8'h00;
    instr_memory[28]  = 8'h10;
    instr_memory[29]  = 8'h00;
    instr_memory[30]  = 8'h00;
    instr_memory[31]  = 8'h00;
    instr_memory[32]  = 8'h01; //pc = pc+9 = 33
    
    instr_memory[33]  = 8'h60; //opq add
    instr_memory[34]  = 8'h9A; //ra and rb pc = pc +2  = 15

    instr_memory[35]  = 8'h60; //opq add
    instr_memory[36]  = 8'h56;

    instr_memory[37]  = 8'h80; //call
    instr_memory[38]  = 8'h00;//8byte destination
    instr_memory[39]  = 8'h00;
    instr_memory[40]  = 8'h00;
    instr_memory[41]  = 8'h10;
    instr_memory[42]  = 8'h00;
    instr_memory[43]  = 8'h00;
    instr_memory[44]  = 8'h11;
    instr_memory[45]  = 8'h01; //pc = pc+9 = 33


    instr_memory[46]  = 8'h00; //halt
    
    
end
    
endmodule

SEQUENTIAL/decode_tb.vcd
$date
	Mon Feb 20 20:50:38 2023
$end
$version
	Icarus Verilog
$end
$timescale
	1s
$end
$scope module decode_tb $end
$var wire 1 ! cnd $end
$var wire 64 " valE [63:0] $end
$var wire 64 # valM [63:0] $end
$var wire 64 $ valc [63:0] $end
$var wire 64 % valP [63:0] $end
$var wire 64 & valB [63:0] $end
$var wire 64 ' valA [63:0] $end
$var wire 64 ( reg_f9 [63:0] $end
$var wire 64 ) reg_f8 [63:0] $end
$var wire 64 * reg_f7 [63:0] $end
$var wire 64 + reg_f6 [63:0] $end
$var wire 64 , reg_f5 [63:0] $end
$var wire 64 - reg_f4 [63:0] $end
$var wire 64 . reg_f3 [63:0] $end
$var wire 64 / reg_f2 [63:0] $end
$var wire 64 0 reg_f14 [63:0] $end
$var wire 64 1 reg_f13 [63:0] $end
$var wire 64 2 reg_f12 [63:0] $end
$var wire 64 3 reg_f11 [63:0] $end
$var wire 64 4 reg_f10 [63:0] $end
$var wire 64 5 reg_f1 [63:0] $end
$var wire 64 6 reg_f0 [63:0] $end
$var wire 4 7 rB [3:0] $end
$var wire 4 8 rA [3:0] $end
$var wire 1 9 mem_error $end
$var wire 1 : invalid_instr $end
$var wire 4 ; ifun [3:0] $end
$var wire 4 < icode [3:0] $end
$var wire 1 = halt $end
$var reg 64 > PC [63:0] $end
$var reg 1 ? clk $end
$var reg 80 @ instr [0:79] $end
$scope module decode_call $end
$var wire 1 ? clk $end
$var wire 1 ! cnd $end
$var wire 64 A valE [63:0] $end
$var wire 64 B valM [63:0] $end
$var wire 4 C rB [3:0] $end
$var wire 4 D rA [3:0] $end
$var wire 4 E icode [3:0] $end
$var reg 64 F reg_f0 [63:0] $end
$var reg 64 G reg_f1 [63:0] $end
$var reg 64 H reg_f10 [63:0] $end
$var reg 64 I reg_f11 [63:0] $end
$var reg 64 J reg_f12 [63:0] $end
$var reg 64 K reg_f13 [63:0] $end
$var reg 64 L reg_f14 [63:0] $end
$var reg 64 M reg_f2 [63:0] $end
$var reg 64 N reg_f3 [63:0] $end
$var reg 64 O reg_f4 [63:0] $end
$var reg 64 P reg_f5 [63:0] $end
$var reg 64 Q reg_f6 [63:0] $end
$var reg 64 R reg_f7 [63:0] $end
$var reg 64 S reg_f8 [63:0] $end
$var reg 64 T reg_f9 [63:0] $end
$var reg 64 U valA [63:0] $end
$var reg 64 V valB [63:0] $end
$upscope $end
$scope module fetch_call $end
$var wire 64 W PC [63:0] $end
$var wire 1 ? clk $end
$var wire 80 X instr [0:79] $end
$var reg 1 = halt $end
$var reg 4 Y icode [3:0] $end
$var reg 4 Z ifun [3:0] $end
$var reg 1 : invalid_instr $end
$var reg 1 9 mem_error $end
$var reg 4 [ rA [3:0] $end
$var reg 4 \ rB [3:0] $end
$var reg 64 ] valP [63:0] $end
$var reg 64 ^ valc [63:0] $end
$upscope $end
$upscope $end
$enddefinitions $end
#0
$dumpvars
bx ^
b10100 ]
bx \
bx [
b0 Z
b1 Y
b10000001000000000000101100000001000111000000000000000000000000000000000010000 X
b10011 W
b0 V
b0 U
bx T
bx S
bx R
bx Q
bx P
bx O
bx N
bx M
bx L
bx K
bx J
bx I
bx H
bx G
bx F
b1 E
bx D
bx C
bz B
bz A
b10000001000000000000101100000001000111000000000000000000000000000000000010000 @
0?
b10011 >
0=
b1 <
b0 ;
0:
09
bx 8
bx 7
bx 6
bx 5
bx 4
bx 3
bx 2
bx 1
bx 0
bx /
bx .
bx -
bx ,
bx +
bx *
bx )
bx (
b0 '
b0 &
b10100 %
bx $
bz #
bz "
1!
$end
#10
b1100 '
b1100 U
b10110 %
b10110 ]
b0 8
b0 D
b0 [
b1 7
b1 C
b1 \
b10 <
b10 E
b10 Y
b100000000000010110000000100011100000000000000000000000000000000001000000000000 @
b100000000000010110000000100011100000000000000000000000000000000001000000000000 X
b10000111000011 0
b10000111000011 L
b11000011111 1
b11000011111 K
b0 2
b0 J
b10011110000000 3
b10011110000000 I
b11000000111001 4
b11000000111001 H
b1111111111111111111111111111111111111111111111111100111111000111 (
b1111111111111111111111111111111111111111111111111100111111000111 T
b11110001101100110000 )
b11110001101100110000 S
b10011100010000 *
b10011100010000 R
b1111111111111111111111111111111111111111111111111111111101110001 +
b1111111111111111111111111111111111111111111111111111111101110001 Q
b110010 ,
b110010 P
b11111110 -
b11111110 O
b11 .
b11 N
b1100101 /
b1100101 M
b1010 5
b1010 G
b1100 6
b1100 F
b10100 >
b10100 W
1?
#20
0?
#30
b11 &
b11 V
b11000 %
b11000 ]
b10 8
b10 D
b10 [
b11 7
b11 C
b11 \
b110 <
b110 E
b110 Y
b1100000001000111000000000000000000000000000000000010000000000000000000000000000 @
b1100000001000111000000000000000000000000000000000010000000000000000000000000000 X
b10110 >
b10110 W
bz 5
bz G
b1100101 '
b1100101 U
1?
#40
0?
#50
b100001 %
b100001 ]
b1000000000000000000000000000000000001 $
b1000000000000000000000000000000000001 ^
b1000 <
b1000 E
b1000 Y
b10000000000000000000000000000000000100000000000000000000000000000000000101100000 @
b10000000000000000000000000000000000100000000000000000000000000000000000101100000 X
bz .
bz N
b11000 >
b11000 W
b11111110 &
b11111110 V
b0 '
b0 U
1?
#60
0?
#70
b1111111111111111111111111111111111111111111111111100111111000111 '
b1111111111111111111111111111111111111111111111111100111111000111 U
b100011 %
b100011 ]
b1001 8
b1001 D
b1001 [
b1010 7
b1010 C
b1010 \
b110 <
b110 E
b110 Y
b1100000100110100110000001010110100000000000000000000000000000000001000000000000 @
b1100000100110100110000001010110100000000000000000000000000000000001000000000000 X
b100001 >
b100001 W
bz -
bz O
b11000000111001 &
b11000000111001 V
1?
#80
0?
#90
b100101 %
b100101 ]
b101 8
b101 D
b101 [
b110 7
b110 C
b110 \
b1100000010101101000000000000000000000000000000000010000000000000000000000010001 @
b1100000010101101000000000000000000000000000000000010000000000000000000000010001 X
bz 4
bz H
b100011 >
b100011 W
b1111111111111111111111111111111111111111111111111111111101110001 &
b1111111111111111111111111111111111111111111111111111111101110001 V
b110010 '
b110010 U
1?
#100
0?
#110
b101110 %
b101110 ]
b1000000000000000000000001000100000001 $
b1000000000000000000000001000100000001 ^
b1000 <
b1000 E
b1000 Y
b10000000000000000000000000000000000100000000000000000000000100010000000100000000 @
b10000000000000000000000000000000000100000000000000000000000100010000000100000000 X
b100101 >
b100101 W
bz +
bz Q
bz &
bz V
b0 '
b0 U
1?
#120
0?
#130
b0 &
b0 V
b101111 %
b101111 ]
1=
b0 <
b0 E
b0 Y
b0xxxxxxxxxxxxxxxxxxxxxxxxxxxxxxxxxxxxxxxxxxxxxxxxxxxxxxxxxxxxxxxxxxxxxxxx @
b0xxxxxxxxxxxxxxxxxxxxxxxxxxxxxxxxxxxxxxxxxxxxxxxxxxxxxxxxxxxxxxxxxxxxxxxx X
b101110 >
b101110 W
1?
